pipelinepy/ImsTokenProvider.py
pipelinepy/__init__.py
pipelinepy-1.0.5.dist-info/METADATA
pipelinepy-1.0.5.dist-info/WHEEL
pipelinepy-1.0.5.dist-info/RECORD
