Metadata-Version: 2.1
Name: pipelinepy
Version: 1.0.5
Summary: An Adobe IMS authorization code flow used with the OAuth Kafka client for Python (kafka-python-ng).
Home-page: https://github.com/cristianpetrache/pipelinepy
Author: Petrut Petrache
Author-email: cpetrache@adobe.com
Requires-Python: >=3.8,<4.0
Classifier: Programming Language :: Python :: 3
Classifier: Programming Language :: Python :: 3.8
Classifier: Programming Language :: Python :: 3.9
Classifier: Programming Language :: Python :: 3.10
Classifier: Programming Language :: Python :: 3.11
Classifier: Programming Language :: Python :: 3.12
Requires-Dist: kafka-python-ng (>=2.2.2,<3.0.0)
Requires-Dist: requests (>=2.31.0,<3.0.0)
Project-URL: Repository, https://github.com/cristianpetrache/pipelinepy
